[
    {
        "timestamp": 1730061000,
        "date": "1403-08-07",
        "open": 66450,
        "high": 67550,
        "low": 66400,
        "close": 67500
    },
    {
        "timestamp": 1730147400,
        "date": "1403-08-08",
        "open": 67500,
        "high": 68700,
        "low": 67500,
        "close": 68550
    },
    {
        "timestamp": 1730233800,
        "date": "1403-08-09",
        "open": 69250,
        "high": 69550,
        "low": 68700,
        "close": 68800
    },
    {
        "timestamp": 1730320200,
        "date": "1403-08-10",
        "open": 68700,
        "high": 68900,
        "low": 68200,
        "close": 68400
    },
    {
        "timestamp": 1730406600,
        "date": "1403-08-11",
        "open": 68400,
        "high": 68600,
        "low": 68350,
        "close": 68450
    },
    {
        "timestamp": 1730493000,
        "date": "1403-08-12",
        "open": 68450,
        "high": 69500,
        "low": 68450,
        "close": 69400
    },
    {
        "timestamp": 1730579400,
        "date": "1403-08-13",
        "open": 69400,
        "high": 70250,
        "low": 69300,
        "close": 69500
    },
    {
        "timestamp": 1730665800,
        "date": "1403-08-14",
        "open": 69750,
        "high": 69900,
        "low": 68700,
        "close": 69100
    },
    {
        "timestamp": 1730752200,
        "date": "1403-08-15",
        "open": 69100,
        "high": 69100,
        "low": 68400,
        "close": 68900
    },
    {
        "timestamp": 1730838600,
        "date": "1403-08-16",
        "open": 69900,
        "high": 70300,
        "low": 69500,
        "close": 69700
    },
    {
        "timestamp": 1730925000,
        "date": "1403-08-17",
        "open": 69700,
        "high": 69700,
        "low": 68950,
        "close": 69350
    },
    {
        "timestamp": 1731011400,
        "date": "1403-08-18",
        "open": 69350,
        "high": 69700,
        "low": 69300,
        "close": 69600
    },
    {
        "timestamp": 1731097800,
        "date": "1403-08-19",
        "open": 69600,
        "high": 69900,
        "low": 69150,
        "close": 69150
    },
    {
        "timestamp": 1731184200,
        "date": "1403-08-20",
        "open": 68950,
        "high": 69350,
        "low": 68250,
        "close": 68350
    },
    {
        "timestamp": 1731270600,
        "date": "1403-08-21",
        "open": 68350,
        "high": 68350,
        "low": 66950,
        "close": 67000
    },
    {
        "timestamp": 1731357000,
        "date": "1403-08-22",
        "open": 67100,
        "high": 68200,
        "low": 67050,
        "close": 68100
    },
    {
        "timestamp": 1731443400,
        "date": "1403-08-23",
        "open": 68100,
        "high": 68600,
        "low": 68000,
        "close": 68100
    },
    {
        "timestamp": 1731529800,
        "date": "1403-08-24",
        "open": 68100,
        "high": 68600,
        "low": 67900,
        "close": 68450
    },
    {
        "timestamp": 1731616200,
        "date": "1403-08-25",
        "open": 68450,
        "high": 68500,
        "low": 68200,
        "close": 68250
    },
    {
        "timestamp": 1731702600,
        "date": "1403-08-26",
        "open": 68250,
        "high": 68600,
        "low": 68100,
        "close": 68450
    },
    {
        "timestamp": 1731789000,
        "date": "1403-08-27",
        "open": 68450,
        "high": 68600,
        "low": 68250,
        "close": 68300
    },
    {
        "timestamp": 1731875400,
        "date": "1403-08-28",
        "open": 68350,
        "high": 68550,
        "low": 68250,
        "close": 68250
    },
    {
        "timestamp": 1731961800,
        "date": "1403-08-29",
        "open": 68500,
        "high": 69250,
        "low": 68400,
        "close": 69150
    },
    {
        "timestamp": 1732048200,
        "date": "1403-08-30",
        "open": 69150,
        "high": 69750,
        "low": 69050,
        "close": 69150
    },
    {
        "timestamp": 1732134600,
        "date": "1403-09-01",
        "open": 69150,
        "high": 69650,
        "low": 69150,
        "close": 69550
    },
    {
        "timestamp": 1732221000,
        "date": "1403-09-02",
        "open": 69550,
        "high": 70050,
        "low": 69500,
        "close": 70050
    },
    {
        "timestamp": 1732307400,
        "date": "1403-09-03",
        "open": 70250,
        "high": 70500,
        "low": 70100,
        "close": 70100
    },
    {
        "timestamp": 1732393800,
        "date": "1403-09-04",
        "open": 70100,
        "high": 70300,
        "low": 68600,
        "close": 69200
    },
    {
        "timestamp": 1732480200,
        "date": "1403-09-05",
        "open": 69200,
        "high": 69600,
        "low": 68650,
        "close": 69400
    },
    {
        "timestamp": 1732566600,
        "date": "1403-09-06",
        "open": 69400,
        "high": 70000,
        "low": 69400,
        "close": 69600
    },
    {
        "timestamp": 1732653000,
        "date": "1403-09-07",
        "open": 69700,
        "high": 69950,
        "low": 69650,
        "close": 69950
    },
    {
        "timestamp": 1732739400,
        "date": "1403-09-08",
        "open": 69950,
        "high": 70150,
        "low": 69700,
        "close": 69950
    },
    {
        "timestamp": 1732825800,
        "date": "1403-09-09",
        "open": 69950,
        "high": 70650,
        "low": 69950,
        "close": 70650
    },
    {
        "timestamp": 1732912200,
        "date": "1403-09-10",
        "open": 70700,
        "high": 71150,
        "low": 70350,
        "close": 70550
    },
    {
        "timestamp": 1732998600,
        "date": "1403-09-11",
        "open": 70600,
        "high": 70850,
        "low": 70130,
        "close": 70350
    },
    {
        "timestamp": 1733085000,
        "date": "1403-09-12",
        "open": 70400,
        "high": 70950,
        "low": 70400,
        "close": 70850
    },
    {
        "timestamp": 1733171400,
        "date": "1403-09-13",
        "open": 70950,
        "high": 71450,
        "low": 70850,
        "close": 71400
    },
    {
        "timestamp": 1733257800,
        "date": "1403-09-14",
        "open": 71400,
        "high": 71950,
        "low": 71350,
        "close": 71950
    },
    {
        "timestamp": 1733344200,
        "date": "1403-09-15",
        "open": 72000,
        "high": 72050,
        "low": 71580,
        "close": 71750
    },
    {
        "timestamp": 1733430600,
        "date": "1403-09-16",
        "open": 71750,
        "high": 71750,
        "low": 71400,
        "close": 71450
    },
    {
        "timestamp": 1733517000,
        "date": "1403-09-17",
        "open": 71450,
        "high": 71850,
        "low": 71250,
        "close": 71650
    },
    {
        "timestamp": 1733603400,
        "date": "1403-09-18",
        "open": 71650,
        "high": 72500,
        "low": 71650,
        "close": 72000
    },
    {
        "timestamp": 1733689800,
        "date": "1403-09-19",
        "open": 72000,
        "high": 72600,
        "low": 72000,
        "close": 72550
    },
    {
        "timestamp": 1733776200,
        "date": "1403-09-20",
        "open": 72550,
        "high": 73200,
        "low": 72450,
        "close": 73200
    },
    {
        "timestamp": 1733862600,
        "date": "1403-09-21",
        "open": 73200,
        "high": 73850,
        "low": 73150,
        "close": 73750
    },
    {
        "timestamp": 1733949000,
        "date": "1403-09-22",
        "open": 73750,
        "high": 73900,
        "low": 73150,
        "close": 73650
    },
    {
        "timestamp": 1734035400,
        "date": "1403-09-23",
        "open": 73650,
        "high": 74200,
        "low": 73620,
        "close": 74150
    },
    {
        "timestamp": 1734121800,
        "date": "1403-09-24",
        "open": 74200,
        "high": 75600,
        "low": 74050,
        "close": 75550
    },
    {
        "timestamp": 1734208200,
        "date": "1403-09-25",
        "open": 75550,
        "high": 75600,
        "low": 74950,
        "close": 75350
    },
    {
        "timestamp": 1734294600,
        "date": "1403-09-26",
        "open": 75300,
        "high": 76700,
        "low": 75250,
        "close": 76650
    },
    {
        "timestamp": 1734381000,
        "date": "1403-09-27",
        "open": 76650,
        "high": 77250,
        "low": 76650,
        "close": 77150
    },
    {
        "timestamp": 1734467400,
        "date": "1403-09-28",
        "open": 77150,
        "high": 77850,
        "low": 77150,
        "close": 77500
    },
    {
        "timestamp": 1734553800,
        "date": "1403-09-29",
        "open": 77800,
        "high": 77950,
        "low": 77250,
        "close": 77300
    },
    {
        "timestamp": 1734899400,
        "date": "1403-10-03",
        "open": 76600,
        "high": 78550,
        "low": 76550,
        "close": 78400
    },
    {
        "timestamp": 1734985800,
        "date": "1403-10-04",
        "open": 78400,
        "high": 79650,
        "low": 78200,
        "close": 79600
    },
    {
        "timestamp": 1735072200,
        "date": "1403-10-05",
        "open": 79600,
        "high": 79800,
        "low": 77800,
        "close": 79300
    },
    {
        "timestamp": 1735158600,
        "date": "1403-10-06",
        "open": 79300,
        "high": 80450,
        "low": 79200,
        "close": 80100
    },
    {
        "timestamp": 1735245000,
        "date": "1403-10-07",
        "open": 80100,
        "high": 80850,
        "low": 80100,
        "close": 80850
    },
    {
        "timestamp": 1735331400,
        "date": "1403-10-08",
        "open": 80850,
        "high": 82250,
        "low": 80850,
        "close": 82100
    },
    {
        "timestamp": 1735417800,
        "date": "1403-10-09",
        "open": 82050,
        "high": 82200,
        "low": 80300,
        "close": 80300
    },
    {
        "timestamp": 1735504200,
        "date": "1403-10-10",
        "open": 80300,
        "high": 82100,
        "low": 80000,
        "close": 82100
    },
    {
        "timestamp": 1735590600,
        "date": "1403-10-11",
        "open": 82050,
        "high": 82150,
        "low": 81100,
        "close": 81650
    },
    {
        "timestamp": 1735677000,
        "date": "1403-10-12",
        "open": 81600,
        "high": 81850,
        "low": 81430,
        "close": 81700
    },
    {
        "timestamp": 1735763400,
        "date": "1403-10-13",
        "open": 81150,
        "high": 81250,
        "low": 80850,
        "close": 80850
    },
    {
        "timestamp": 1735849800,
        "date": "1403-10-14",
        "open": 80500,
        "high": 80500,
        "low": 80350,
        "close": 80350
    },
    {
        "timestamp": 1735936200,
        "date": "1403-10-15",
        "open": 80150,
        "high": 80350,
        "low": 79650,
        "close": 80350
    },
    {
        "timestamp": 1736022600,
        "date": "1403-10-16",
        "open": 80500,
        "high": 80500,
        "low": 79800,
        "close": 79850
    },
    {
        "timestamp": 1736109000,
        "date": "1403-10-17",
        "open": 79550,
        "high": 80150,
        "low": 79450,
        "close": 80150
    },
    {
        "timestamp": 1736195400,
        "date": "1403-10-18",
        "open": 80400,
        "high": 80750,
        "low": 79950,
        "close": 80300
    },
    {
        "timestamp": 1736281800,
        "date": "1403-10-19",
        "open": 80400,
        "high": 81150,
        "low": 80200,
        "close": 80750
    },
    {
        "timestamp": 1736368200,
        "date": "1403-10-20",
        "open": 81350,
        "high": 81900,
        "low": 81350,
        "close": 81800
    },
    {
        "timestamp": 1736454600,
        "date": "1403-10-21",
        "open": 82100,
        "high": 82250,
        "low": 82100,
        "close": 82250
    },
    {
        "timestamp": 1736541000,
        "date": "1403-10-22",
        "open": 82450,
        "high": 82500,
        "low": 82200,
        "close": 82200
    },
    {
        "timestamp": 1736627400,
        "date": "1403-10-23",
        "open": 82050,
        "high": 82050,
        "low": 81020,
        "close": 81050
    },
    {
        "timestamp": 1736713800,
        "date": "1403-10-24",
        "open": 81250,
        "high": 81950,
        "low": 81250,
        "close": 81550
    },
    {
        "timestamp": 1736800200,
        "date": "1403-10-25",
        "open": 81650,
        "high": 81850,
        "low": 81650,
        "close": 81780
    },
    {
        "timestamp": 1736886600,
        "date": "1403-10-26",
        "open": 81600,
        "high": 81600,
        "low": 80780,
        "close": 80780
    },
    {
        "timestamp": 1736973000,
        "date": "1403-10-27",
        "open": 80350,
        "high": 80600,
        "low": 80350,
        "close": 80550
    },
    {
        "timestamp": 1737059400,
        "date": "1403-10-28",
        "open": 80150,
        "high": 80150,
        "low": 80000,
        "close": 80000
    },
    {
        "timestamp": 1737145800,
        "date": "1403-10-29",
        "open": 80350,
        "high": 81000,
        "low": 80300,
        "close": 81000
    },
    {
        "timestamp": 1737232200,
        "date": "1403-10-30",
        "open": 81200,
        "high": 81300,
        "low": 81050,
        "close": 81050
    },
    {
        "timestamp": 1737318600,
        "date": "1403-11-01",
        "open": 81300,
        "high": 81600,
        "low": 81080,
        "close": 81350
    },
    {
        "timestamp": 1737405000,
        "date": "1403-11-02",
        "open": 82100,
        "high": 82800,
        "low": 82100,
        "close": 82800
    },
    {
        "timestamp": 1737491400,
        "date": "1403-11-03",
        "open": 82850,
        "high": 83200,
        "low": 82700,
        "close": 82900
    },
    {
        "timestamp": 1737577800,
        "date": "1403-11-04",
        "open": 83500,
        "high": 84350,
        "low": 83500,
        "close": 84050
    },
    {
        "timestamp": 1737664200,
        "date": "1403-11-05",
        "open": 83500,
        "high": 83500,
        "low": 83300,
        "close": 83350
    },
    {
        "timestamp": 1737750600,
        "date": "1403-11-06",
        "open": 83500,
        "high": 83950,
        "low": 83500,
        "close": 83900
    },
    {
        "timestamp": 1737837000,
        "date": "1403-11-07",
        "open": 84050,
        "high": 84350,
        "low": 83950,
        "close": 84250
    },
    {
        "timestamp": 1737923400,
        "date": "1403-11-08",
        "open": 84200,
        "high": 84500,
        "low": 83950,
        "close": 84330
    },
    {
        "timestamp": 1738009800,
        "date": "1403-11-09",
        "open": 84250,
        "high": 84700,
        "low": 84250,
        "close": 84450
    },
    {
        "timestamp": 1738096200,
        "date": "1403-11-10",
        "open": 84050,
        "high": 84150,
        "low": 83480,
        "close": 83650
    },
    {
        "timestamp": 1738182600,
        "date": "1403-11-11",
        "open": 83650,
        "high": 83950,
        "low": 83480,
        "close": 83950
    },
    {
        "timestamp": 1738269000,
        "date": "1403-11-12",
        "open": 83950,
        "high": 83950,
        "low": 83850,
        "close": 83850
    },
    {
        "timestamp": 1738355400,
        "date": "1403-11-13",
        "open": 83950,
        "high": 84300,
        "low": 83950,
        "close": 84280
    },
    {
        "timestamp": 1738441800,
        "date": "1403-11-14",
        "open": 84450,
        "high": 84900,
        "low": 84430,
        "close": 84450
    },
    {
        "timestamp": 1738528200,
        "date": "1403-11-15",
        "open": 84800,
        "high": 84800,
        "low": 84080,
        "close": 84220
    },
    {
        "timestamp": 1738614600,
        "date": "1403-11-16",
        "open": 84200,
        "high": 85050,
        "low": 84200,
        "close": 84950
    },
    {
        "timestamp": 1738701000,
        "date": "1403-11-17",
        "open": 85100,
        "high": 85850,
        "low": 85100,
        "close": 85750
    },
    {
        "timestamp": 1738787400,
        "date": "1403-11-18",
        "open": 85700,
        "high": 86100,
        "low": 85700,
        "close": 86100
    },
    {
        "timestamp": 1738873800,
        "date": "1403-11-19",
        "open": 86100,
        "high": 87050,
        "low": 86100,
        "close": 86900
    },
    {
        "timestamp": 1738960200,
        "date": "1403-11-20",
        "open": 88550,
        "high": 89850,
        "low": 88300,
        "close": 89700
    },
    {
        "timestamp": 1739046600,
        "date": "1403-11-21",
        "open": 90050,
        "high": 92750,
        "low": 89950,
        "close": 92750
    },
    {
        "timestamp": 1739133000,
        "date": "1403-11-22",
        "open": 92650,
        "high": 93800,
        "low": 89700,
        "close": 92200
    },
    {
        "timestamp": 1739219400,
        "date": "1403-11-23",
        "open": 92450,
        "high": 92450,
        "low": 87800,
        "close": 89350
    },
    {
        "timestamp": 1739305800,
        "date": "1403-11-24",
        "open": 89000,
        "high": 89320,
        "low": 88350,
        "close": 89320
    },
    {
        "timestamp": 1739392200,
        "date": "1403-11-25",
        "open": 89250,
        "high": 89950,
        "low": 89250,
        "close": 89950
    },
    {
        "timestamp": 1739478600,
        "date": "1403-11-26",
        "open": 90300,
        "high": 90900,
        "low": 90300,
        "close": 90900
    },
    {
        "timestamp": 1739565000,
        "date": "1403-11-27",
        "open": 91550,
        "high": 91550,
        "low": 90850,
        "close": 91250
    },
    {
        "timestamp": 1739651400,
        "date": "1403-11-28",
        "open": 90800,
        "high": 91450,
        "low": 90300,
        "close": 91270
    },
    {
        "timestamp": 1739737800,
        "date": "1403-11-29",
        "open": 91550,
        "high": 91750,
        "low": 91350,
        "close": 91450
    },
    {
        "timestamp": 1739824200,
        "date": "1403-11-30",
        "open": 91600,
        "high": 92600,
        "low": 91600,
        "close": 92450
    },
    {
        "timestamp": 1739910600,
        "date": "1403-12-01",
        "open": 92550,
        "high": 93450,
        "low": 92550,
        "close": 92730
    },
    {
        "timestamp": 1739997000,
        "date": "1403-12-02",
        "open": 93400,
        "high": 94000,
        "low": 93400,
        "close": 94000
    },
    {
        "timestamp": 1740083400,
        "date": "1403-12-03",
        "open": 93500,
        "high": 93700,
        "low": 93500,
        "close": 93600
    },
    {
        "timestamp": 1740169800,
        "date": "1403-12-04",
        "open": 94600,
        "high": 94900,
        "low": 93750,
        "close": 93750
    },
    {
        "timestamp": 1740256200,
        "date": "1403-12-05",
        "open": 93800,
        "high": 93950,
        "low": 92850,
        "close": 93250
    },
    {
        "timestamp": 1740342600,
        "date": "1403-12-06",
        "open": 93400,
        "high": 93450,
        "low": 92250,
        "close": 92350
    },
    {
        "timestamp": 1740429000,
        "date": "1403-12-07",
        "open": 92100,
        "high": 93000,
        "low": 91800,
        "close": 93000
    },
    {
        "timestamp": 1740515400,
        "date": "1403-12-08",
        "open": 93700,
        "high": 94150,
        "low": 93220,
        "close": 93220
    },
    {
        "timestamp": 1740601800,
        "date": "1403-12-09",
        "open": 93500,
        "high": 93700,
        "low": 92950,
        "close": 93000
    },
    {
        "timestamp": 1740688200,
        "date": "1403-12-10",
        "open": 93050,
        "high": 93250,
        "low": 93050,
        "close": 93100
    },
    {
        "timestamp": 1740774600,
        "date": "1403-12-11",
        "open": 93000,
        "high": 93300,
        "low": 92500,
        "close": 92700
    },
    {
        "timestamp": 1740861000,
        "date": "1403-12-12",
        "open": 93000,
        "high": 93950,
        "low": 92100,
        "close": 92600
    },
    {
        "timestamp": 1740947400,
        "date": "1403-12-13",
        "open": 92650,
        "high": 92750,
        "low": 91300,
        "close": 91350
    },
    {
        "timestamp": 1741033800,
        "date": "1403-12-14",
        "open": 91200,
        "high": 91750,
        "low": 91000,
        "close": 91050
    },
    {
        "timestamp": 1741120200,
        "date": "1403-12-15",
        "open": 90550,
        "high": 90550,
        "low": 89000,
        "close": 89000
    },
    {
        "timestamp": 1741206600,
        "date": "1403-12-16",
        "open": 89000,
        "high": 90250,
        "low": 88850,
        "close": 89600
    },
    {
        "timestamp": 1741293000,
        "date": "1403-12-17",
        "open": 90500,
        "high": 90550,
        "low": 90150,
        "close": 90250
    },
    {
        "timestamp": 1741379400,
        "date": "1403-12-18",
        "open": 91200,
        "high": 92450,
        "low": 91150,
        "close": 91850
    },
    {
        "timestamp": 1741465800,
        "date": "1403-12-19",
        "open": 92050,
        "high": 92950,
        "low": 92050,
        "close": 92700
    },
    {
        "timestamp": 1741552200,
        "date": "1403-12-20",
        "open": 94050,
        "high": 94100,
        "low": 92600,
        "close": 93030
    },
    {
        "timestamp": 1741638600,
        "date": "1403-12-21",
        "open": 93050,
        "high": 93500,
        "low": 92850,
        "close": 93150
    },
    {
        "timestamp": 1741725000,
        "date": "1403-12-22",
        "open": 93350,
        "high": 93350,
        "low": 92950,
        "close": 93250
    },
    {
        "timestamp": 1741811400,
        "date": "1403-12-23",
        "open": 93500,
        "high": 93550,
        "low": 92850,
        "close": 92850
    },
    {
        "timestamp": 1741897800,
        "date": "1403-12-24",
        "open": 92600,
        "high": 92700,
        "low": 92580,
        "close": 92580
    },
    {
        "timestamp": 1741984200,
        "date": "1403-12-25",
        "open": 91500,
        "high": 91950,
        "low": 91300,
        "close": 91900
    },
    {
        "timestamp": 1742070600,
        "date": "1403-12-26",
        "open": 92500,
        "high": 94000,
        "low": 92500,
        "close": 94000
    },
    {
        "timestamp": 1742157000,
        "date": "1403-12-27",
        "open": 94400,
        "high": 95350,
        "low": 94400,
        "close": 95350
    },
    {
        "timestamp": 1742243400,
        "date": "1403-12-28",
        "open": 98000,
        "high": 98800,
        "low": 97400,
        "close": 98600
    },
    {
        "timestamp": 1742329800,
        "date": "1403-12-29",
        "open": 98800,
        "high": 98800,
        "low": 98450,
        "close": 98450
    },
    {
        "timestamp": 1742416200,
        "date": "1403-12-30",
        "open": 98250,
        "high": 98750,
        "low": 98250,
        "close": 98300
    }
]